<!DOCTYPE codename-engine-stage>
<stage cameraSpeed="0.5" folder="stages/lord x/" name="cycles-hills" zoom="0.5">
	<sprite x="345" sprite="sky" y="-705" scale="2.95" name="sky"/>
	<sprite x="240" sprite="hills2" y="-305" scale="2.5" name="hill2"/>
	<sprite x="150" sprite="hills1" y="-255" scale="2.5" name="hill"/>
	<sprite x="-815" sprite="floor" y="140" scale="1.4" name="ground"/>
	<sprite x="2000" sprite="tree" y="-870" name="tree"/>
	<sprite x="-250" sprite="smallflowe2" y="-750" name="flower2"/>
	<sprite x="960" sprite="NotKnuckles_Assets" y="-260" scale="2.5" name="notknuckles"/>
	<sprite x="-205" sprite="WeirdAssFlower_Assets" y="-580" name="eyeflower"/>
	<sprite x="-620" sprite="smallflower" y="-265" type="none" name="flower11"/>
	<opponent scale="1.25" x="185" y="-125"/>
	<sprite x="-270" sprite="smallflower" y="460" name="flower3"/>
	<boyfriend scale="1.25" x="1600" y="-35"/>
	<girlfriend scale="1.25" x="7050" y="-220"/>
	<ratings x="1500"/>
</stage>
